ursamirror/__about__.py
ursamirror/__init__.py
ursamirror/online2std.py
ursamirror/paper2std.py
ursamirror/star_process.py
ursamirror/utils/__init__.py
ursamirror/utils/complete_border.py
ursamirror/utils/star_equations.py
ursamirror/utils/transformations.py
ursamirror/utils/utils.py
ursamirror-0.2.4.dist-info/METADATA
ursamirror-0.2.4.dist-info/WHEEL
ursamirror-0.2.4.dist-info/licenses/LICENSE.txt
ursamirror-0.2.4.dist-info/RECORD
