Metadata-Version: 2.4
Name: ursamirror
Version: 0.2.4
Summary: A Python package for the analysis of the Mirror Tracing Task in polar coordinates
Project-URL: Documentation, https://github.com/PabloFGarrido/ursamirror#readme
Project-URL: Issues, https://github.com/PabloFGarrido/ursamirror/issues
Project-URL: Source, https://github.com/PabloFGarrido/ursamirror
Author-email: "Pablo F. Garrido" <f.garrido.pablo@gmail.com>
Maintainer-email: "Pablo F. Garrido" <f.garrido.pablo@gmail.com>, Emilie Sogn Falch  <emilie.falch@gmail.com>
License-Expression: MIT
License-File: LICENSE.txt
Classifier: Development Status :: 4 - Beta
Classifier: Framework :: IPython
Classifier: Framework :: Jupyter
Classifier: Framework :: Pytest
Classifier: Intended Audience :: Education
Classifier: Intended Audience :: Science/Research
Classifier: License :: OSI Approved :: MIT License
Classifier: Natural Language :: English
Classifier: Operating System :: OS Independent
Classifier: Programming Language :: Python
Classifier: Programming Language :: Python :: 3.9
Classifier: Programming Language :: Python :: 3.10
Classifier: Programming Language :: Python :: 3.11
Classifier: Programming Language :: Python :: 3.12
Classifier: Topic :: Education
Classifier: Topic :: Scientific/Engineering
Classifier: Topic :: Scientific/Engineering :: Image Processing
Requires-Python: >=3.9
Requires-Dist: matplotlib
Requires-Dist: numpy
Requires-Dist: pandas
Requires-Dist: scikit-image
Requires-Dist: scipy
